{"title":"Sitefinity 3.x Windows 7 64-bit Installation","needsFixing":false,"content":"Just had a hard time installing Sitefinity 3.7 SP1 Project Manager on my 64-bit Windows 7 PC.  I was getting a generic 401 IIS Error.\n\nTurns out there’s a step missing from the installation doc…turn on Enable 32-bit Applications on the Classic ASP.NET AppPool! :)","featuredImage":"/images/stock/500x280/img21.jpg","seoDescription":"Getting Sitefinity 3.x up and running on windows 7 64","seoMetaImage":"/images/stock/500x280/img21.jpg","publishedAt":"2012-03-16T02:25:41.2800000Z","slug":"sitefinity-windows-7-64-bit-installation","legacyUrl":"/code/2012/03/16/sitefinity-windows-7-64-bit-installation","markdown":true,"tags":["Tutorial"]}